daffi/__about__.py
daffi/__init__.py
daffi/async_result.py
daffi/exceptions.py
daffi/execution_modifiers.py
daffi/globals.py
daffi/interface.py
daffi/ipc.py
daffi/method_executors.py
daffi/remote_call.py
daffi/settings.py
daffi/signals.py
daffi/store.py
daffi/well_known_callbacks.py
daffi/components/__init__.py
daffi/components/controller.py
daffi/components/node.py
daffi/components/scheduler.py
daffi/components/operations/__init__.py
daffi/components/operations/channel_store.py
daffi/components/operations/controller_operations.py
daffi/components/operations/freezable_queue.py
daffi/components/operations/node_operations.py
daffi/components/operations/streams_store.py
daffi/components/operations/task_waiter.py
daffi/components/operations/ttl_store.py
daffi/components/proto/__init__.py
daffi/components/proto/message.py
daffi/components/proto/messager.proto
daffi/components/proto/messager_pb2.py
daffi/components/proto/messager_pb2_grpc.py
daffi/decorators/__init__.py
daffi/decorators/_alias.py
daffi/decorators/_base.py
daffi/decorators/_callback.py
daffi/decorators/_fetcher.py
daffi/decorators/_local.py
daffi/registry/__init__.py
daffi/registry/_base.py
daffi/registry/_callback.py
daffi/registry/_fetcher.py
daffi/utils/__init__.py
daffi/utils/colors.py
daffi/utils/custom_types.py
daffi/utils/debug.py
daffi/utils/func_validation.py
daffi/utils/logger.py
daffi/utils/misc.py
daffi/utils/timeparse.py
daffi-2.2.1.dist-info/METADATA
daffi-2.2.1.dist-info/WHEEL
daffi-2.2.1.dist-info/licenses/LICENSE.txt
daffi-2.2.1.dist-info/RECORD
