Metadata-Version: 2.1
Name: daffi
Version: 2.2.1
Summary: Daffi is fast, simple and lightweight library for inter process communication
Project-URL: Documentation, https://600apples.github.io/dafi/
Project-URL: Source, https://github.com/600apples/dafi
Author-email: Volodymyr Boiko <600apples@gmail.com>
License-Expression: MIT
License-File: LICENSE.txt
Keywords: async,distributed,grpc,job,python,queue,rpc,stream,task
Classifier: Development Status :: 4 - Beta
Classifier: Intended Audience :: Developers
Classifier: Intended Audience :: System Administrators
Classifier: License :: OSI Approved :: MIT License
Classifier: Operating System :: OS Independent
Classifier: Programming Language :: Python :: 3
Classifier: Programming Language :: Python :: 3.8
Classifier: Programming Language :: Python :: 3.9
Classifier: Programming Language :: Python :: 3.10
Classifier: Topic :: Internet
Classifier: Topic :: Software Development :: Libraries :: Python Modules
Classifier: Topic :: Software Development :: Object Brokering
Classifier: Topic :: Software Development :: Testing
Classifier: Topic :: System :: Clustering
Classifier: Topic :: System :: Distributed Computing
Classifier: Topic :: System :: Monitoring
Classifier: Topic :: System :: Networking
Classifier: Topic :: System :: Systems Administration
Requires-Python: >=3.8
Requires-Dist: anyio>=3.6.2
Requires-Dist: cached-property>=1.5.2
Requires-Dist: cachetools>=5.3.0
Requires-Dist: colorama>=0.4.6; sys_platform == 'win32'
Requires-Dist: dill>=0.3.6
Requires-Dist: grpcio>=1.51.3
Requires-Dist: protobuf>=4.21.12
Requires-Dist: tblib>=1.7.0
Requires-Dist: tenacity>=8.1.0
Requires-Dist: typing-extensions>=4.4.0
Requires-Dist: uvloop>=0.17.0; sys_platform != 'win32'
